{
  "instrumentName": "EQSANS",
  "iptsNumber": "19800",
  "runNumber": "88980",
  "thickness": ".1",
  "outputFileName": "EQSANS_88980",
  "transmission": {
    "runNumber": "88980",
    "value": ""
  },
  "background": {
    "runNumber": "88978",
    "transmission": {
      "runNumber": "88974",
      "value": ""
    }
  },
  "beamCenter": {
    "runNumber": "88973"
  },
  "empty": {
    "runNumber": "88973"
  },
  "configuration": {
    "outputDir": "/tmp/shared/shaman/",
    "sampleApertureSize": "30",
    "sourceApertureDiameter": "",
    "useMaskFileName": true,
    "maskFileName": "/SNS/EQSANS/shared/NeXusFiles/EQSANS/2017B_mp/beamstop60_mask_4m.nxs",
    "useDefaultMask": false,
    "normalization": "Total charge",
    "fluxMonitorRatioFile": "/SNS/EQSANS/IPTS-24769/shared/EQSANS_110943.out",
    "beamFluxFileName": "/SNS/EQSANS/shared/instrument_configuration/bl6_flux_at_sample",
    "useDarkFileName": true,
    "darkFileName": "/SNS/EQSANS/shared/NeXusFiles/EQSANS/2017B_mp/EQSANS_86275.nxs.h5",
    "useSensitivityFileName": false,
    "sensitivityFileName": "/SNS/EQSANS/shared/NeXusFiles/EQSANS/2017A_mp/Sensitivity_patched_thinPMMA_4m_79165_event.nxs",
    "absoluteScaleMethod": "standard",
    "StandardAbsoluteScale": "0.0208641883",
    "useSampleOffset": true,
    "sampleOffset": "0",
    "useDetectorOffset": true,
    "detectorOffset": "0",
    "useSolidAngleCorrection": true,
    "useThetaDepTransCorrection": true,
    "mmRadiusForTransmission": "25.0",
    "numQxQyBins": "80",
    "1DQbinType": "scalar",
    "QbinType": "linear",
    "numQBins": "120",
    "LogQBinsPerDecade": "",
    "LogQBinsDecadeCenter": false,
    "LogQBinsEvenDecade": false,
    "WedgeMinAngles": "-30, 60",
    "WedgeMaxAngles": "30, 120",
    "autoWedgeQmin": "",
    "autoWedgeQmax": "",
    "autoWedgeQdelta": "",
    "autoWedgeAzimuthal_delta": "",
    "autoWedgePeakWidth": "",
    "autoWedgeBackgroundWidth": "",
    "autoWedgeSignalToNoiseMin": "",
    "AnnularAngleBin": "5",
    "Qmin": "",
    "Qmax": "",
    "useErrorWeighting": false,
    "TOFmin": "500.0",
    "TOFmax": "2000.0",
    "useMaskBackTubes": false,
    "wavelengthStepType": "constant lambda",
    "wavelengthStep": "0.1",
    "smearingPixelSizeX": "",
    "smearingPixelSizeY": "",
    "timeslice": false,
    "timesliceinterval": "300.0",
    "logslice": false,
    "logslicename": "",
    "logsliceinterval": "10.0"
  }
}
